unittest_templates/__init__.py
unittest_templates/api.py
unittest_templates/py.typed
unittest_templates/version.py
unittest_templates-0.1.0.dist-info/LICENSE
unittest_templates-0.1.0.dist-info/METADATA
unittest_templates-0.1.0.dist-info/WHEEL
unittest_templates-0.1.0.dist-info/top_level.txt
unittest_templates-0.1.0.dist-info/RECORD
