Metadata-Version: 2.1
Name: unittest-templates
Version: 0.1.0
Summary: Write less unittest boilerplate.
Home-page: https://github.com/cthoyt/unittest-templates
Download-URL: https://github.com/cthoyt/unittest-templates/releases
Author: Charles Tapley Hoyt and Max Berrendorf
Author-email: cthoyt@gmail.com
Maintainer: Charles Tapley Hoyt and Max Berrendorf
Maintainer-email: cthoyt@gmail.com
License: MIT
Project-URL: Bug Tracker, https://github.com/cthoyt/unittest-templates/issues
Project-URL: Source Code, https://github.com/cthoyt/unittest-templates
Keywords: snekpack,cookiecutter,testing,unit testing,generics
Classifier: Development Status :: 1 - Planning
Classifier: Environment :: Console
Classifier: Intended Audience :: Developers
Classifier: License :: OSI Approved :: MIT License
Classifier: Operating System :: OS Independent
Classifier: Framework :: Pytest
Classifier: Framework :: tox
Classifier: Framework :: Sphinx
Classifier: Programming Language :: Python
Classifier: Programming Language :: Python :: 3.7
Classifier: Programming Language :: Python :: 3.8
Classifier: Programming Language :: Python :: 3.9
Classifier: Programming Language :: Python :: 3.10
Classifier: Programming Language :: Python :: 3.11
Classifier: Programming Language :: Python :: 3 :: Only
Requires-Python: >=3.7
License-File: LICENSE
Provides-Extra: docs
Requires-Dist: sphinx ; extra == 'docs'
Requires-Dist: sphinx-rtd-theme ; extra == 'docs'
Requires-Dist: sphinx-autodoc-typehints ; extra == 'docs'
Requires-Dist: sphinx-automodapi ; extra == 'docs'
Provides-Extra: tests
Requires-Dist: pytest ; extra == 'tests'
Requires-Dist: coverage ; extra == 'tests'
